st_bridge/__init__.py
st_bridge/bridge/.gitignore
st_bridge/bridge/build/asset-manifest.json
st_bridge/bridge/build/bootstrap.min.css
st_bridge/bridge/build/bootstrap.min.css.map
st_bridge/bridge/build/index.html
st_bridge/bridge/build/precache-manifest.fad985818978633f1a71f25d0a3349e9.js
st_bridge/bridge/build/service-worker.js
st_bridge/bridge/build/static/js/2.d57250d1.chunk.js
st_bridge/bridge/build/static/js/2.d57250d1.chunk.js.LICENSE.txt
st_bridge/bridge/build/static/js/2.d57250d1.chunk.js.map
st_bridge/bridge/build/static/js/main.4c504d7b.chunk.js
st_bridge/bridge/build/static/js/main.4c504d7b.chunk.js.map
st_bridge/bridge/build/static/js/runtime-main.f43d5da3.js
st_bridge/bridge/build/static/js/runtime-main.f43d5da3.js.map
st_bridge/bridge/package-lock.json
st_bridge/bridge/package.json
st_bridge/bridge/public/bootstrap.min.css
st_bridge/bridge/public/bootstrap.min.css.map
st_bridge/bridge/public/index.html
st_bridge/bridge/src/index.tsx
st_bridge/bridge/src/react-app-env.d.ts
st_bridge/bridge/tsconfig.json
st_bridge/bridge/yarn.lock
st_bridge/bridge.py
st_bridge/html/.gitignore
st_bridge/html/build/asset-manifest.json
st_bridge/html/build/bootstrap.min.css
st_bridge/html/build/bootstrap.min.css.map
st_bridge/html/build/index.html
st_bridge/html/build/precache-manifest.5b5300284d43bf8ba972ca3da2f90d8d.js
st_bridge/html/build/service-worker.js
st_bridge/html/build/static/js/2.ce2c8f1c.chunk.js
st_bridge/html/build/static/js/2.ce2c8f1c.chunk.js.LICENSE.txt
st_bridge/html/build/static/js/2.ce2c8f1c.chunk.js.map
st_bridge/html/build/static/js/main.4e83250e.chunk.js
st_bridge/html/build/static/js/main.4e83250e.chunk.js.map
st_bridge/html/build/static/js/runtime-main.d8806d63.js
st_bridge/html/build/static/js/runtime-main.d8806d63.js.map
st_bridge/html/package-lock.json
st_bridge/html/package.json
st_bridge/html/public/bootstrap.min.css
st_bridge/html/public/bootstrap.min.css.map
st_bridge/html/public/index.html
st_bridge/html/src/index.tsx
streamlit_bridge-1.1.3.dist-info/LICENSE
streamlit_bridge-1.1.3.dist-info/WHEEL
streamlit_bridge-1.1.3.dist-info/METADATA
streamlit_bridge-1.1.3.dist-info/RECORD
